pyspherex/__init__.py
pyspherex/calculus.py
pyspherex/core.py
pyspherex-1.0.dist-info/LICENSE
pyspherex-1.0.dist-info/METADATA
pyspherex-1.0.dist-info/WHEEL
pyspherex-1.0.dist-info/top_level.txt
pyspherex-1.0.dist-info/RECORD
