Metadata-Version: 2.1
Name: pyspherex
Version: 1.0
Summary: Python tool to perform spherical harmonics expansion.
Home-page: https://github.com/marstaa/PySphereX
Author: Martin Staab
Author-email: martin.staab@aei.mpg.de
License: UNKNOWN
Keywords: sperical harmonics,expansion
Platform: UNKNOWN
Classifier: Intended Audience :: Science/Research
Classifier: Topic :: Scientific/Engineering
Classifier: License :: OSI Approved :: BSD License
Classifier: Programming Language :: Python :: 3.7
Classifier: Programming Language :: Python :: 3.8
Classifier: Programming Language :: Python :: 3.9
Requires-Python: >=3.7
License-File: LICENSE
Requires-Dist: numpy
